CHANGES.txt
DEPENDENCES.txt
README.txt
setup.py
src/__init__.py
src/ng/__init__.py
src/ng.site.addon.rubricator.egg-info/PKG-INFO
src/ng.site.addon.rubricator.egg-info/SOURCES.txt
src/ng.site.addon.rubricator.egg-info/dependency_links.txt
src/ng.site.addon.rubricator.egg-info/namespace_packages.txt
src/ng.site.addon.rubricator.egg-info/not-zip-safe
src/ng.site.addon.rubricator.egg-info/requires.txt
src/ng.site.addon.rubricator.egg-info/top_level.txt
src/ng/site/__init__.py
src/ng/site/addon/__init__.py
src/ng/site/addon/rubricator/__init__.py
src/ng/site/addon/rubricator/configure.zcml
src/ng/site/addon/rubricator/ng.site.addon.rubricator.txt
src/ng/site/addon/rubricator/contain/__init__.py
src/ng/site/addon/rubricator/contain/configure.zcml
src/ng/site/addon/rubricator/contain/interfaces.py
src/ng/site/addon/rubricator/etc/ng.site.addon.rubricator-configure.zcml
src/ng/site/addon/rubricator/install/__init__.py
src/ng/site/addon/rubricator/install/configure.zcml
src/ng/site/addon/rubricator/install/install_content.py
src/ng/site/addon/rubricator/install/install_rubricator.py
src/ng/site/addon/rubricator/rubric/__init__.py
src/ng/site/addon/rubricator/rubric/configure.zcml